mycalc043/sum.py
mycalc043-0.0.1.dist-info/METADATA
mycalc043-0.0.1.dist-info/WHEEL
mycalc043-0.0.1.dist-info/top_level.txt
mycalc043-0.0.1.dist-info/RECORD
