Metadata-Version: 2.1
Name: mycalc043
Version: 0.0.1
Summary: prefix sum
Home-page: https://github.com/seungmin02/mycalc043
Download-URL: https://github.com/seungmin02/mycalc043/
Author: lsm
Classifier: Programming Language :: Python :: 3
